<?xml version="1.0" encoding="UTF-8"?>
<words>
  <entry>
    <word>اسم</word>
    <int>
      <pron>(اِ+سْ+مْ+يا اِ+سَ+مْ )</pron>
      <gram>[ ع ، اس ، مذ ، وا، ج : اسمونه ]</gram>
      <poem>اِبتداء کوم په اِسم د مولٰی&lt;br/&gt;چې په حکم کښې ئې دي ارض و سماء     (علي خان)&lt;br/&gt;نور چې اِسم ئې خوانده کړو&lt;br/&gt;نرۍ ستن ئې شهزاده کړو             (رشيد)</poem>
      <meanings>
        <meaning>نوم ، نامه</meaning>
        <meaning>جادو ، سحر</meaning>
        <meaning>هغه کلمه چې هغه په خپله معنٰى په خپله دلالت کوي او د څۀ زمانې پابند نۀ وي لکه : د چاسړي، ځاے يا څيز نوم</meaning>
      </meanings>
    </int>
  </entry>
<entry><word>اسم اۤله</word><int><pron/><gram>(اص)</gram><poem/><meanings><meaning>هغه اسم چې د اوازر معنې ورکوي لکه : چاقو ، توره ، ټوپک او توپه او داسې نور</meaning></meanings></int></entry><entry><word>اسم اشاره</word><int><pron/><gram>(اص)</gram><poem/><meanings><meaning>هغه کلمه چې د اشارې دپاره استعمالېږي  لکه : دا هغه او داسې نور</meaning></meanings></int></entry><entry><word>اسم اعظم</word><int><pron/><gram>(اص)</gram><poem/><meanings><meaning>د الله پاک په نومونو کښې يو لوے نوم</meaning></meanings></int></entry><entry><word>اسم تصغير</word><int><pron/><gram>(اص)</gram><poem/><meanings><meaning>هغه اسم چې د چا فرد يا څيز ورکوټوالے ترې څرګندېږي لکه : د چرګ نه چرګوړے ، د دېګ نه دېګچے او داسې نور</meaning></meanings></int></entry><entry><word>اسم جامد</word><int><pron/><gram>(اص)</gram><poem/><meanings><meaning>هغه اسم چې نۀ د څۀ کلمې نه وتے وي او نۀ ورنه څۀ کلمه وځي لکه خر ، اس ، او داسې نور</meaning></meanings></int></entry><entry><word>اسم جلالي</word><int><pron/><gram>(اص)</gram><poem/><meanings><meaning>د خداے پاک هغه نوم چې د جلال شان ئې ترې ظاهر وي لکه جبار ، قهار</meaning></meanings></int></entry><entry><word>اسم جمالي</word><int><pron/><gram>(اص)</gram><poem/><meanings><meaning>د خداے پاک هغه نوم چې جمالي صفات ئې ترې ظاهره وي لکه رحمان ، رحيم او داسې نور</meaning></meanings></int></entry><entry><word>اسم جمع</word><int><pron/><gram>(اص)</gram><poem/><meanings><meaning>هغه اسم چې وي مفرد (يواځې) ولې معنې د ډېر ورکوي لکه لښکر، ټولے، او داسې نور</meaning></meanings></int></entry><entry><word>اسم جنس</word><int><pron/><gram>(اص)</gram><poem/><meanings><meaning>هغه اسم چې د هر يو څيز د نوم دپاره استعمالېږي لکه : ’’ښځه ، اس ، بوټے او داسې نور ‘‘ (په حواله د عربۍ)</meaning></meanings></int></entry><entry><word>اسم حاليه</word><int><pron/><gram>(اص)</gram><poem/><meanings><meaning>دا هغه اسم دے چې د فعل حالت ترې ظاهرېږي لکه : ’’په خندا خندا کښې ئې ووے ‘‘ په سترګو سترګوکښې ‘‘</meaning></meanings></int></entry><entry><word>اسم ذات</word><int><pron/><gram>(اص)</gram><poem/><meanings><meaning/><meaning>الله ، کنايةً هغه نوم چې د هغه په ذات دلالت کوي</meaning><meaning>هغه اسم دے چې د هغه په وجه د څۀ څيز حقيقت د نورو نه جدا څرګند شي</meaning></meanings></int></entry><entry><word>اسم زمان</word><int><pron/><gram/><poem/><meanings><meaning>هغه اسم دے چې وخت ترې ظاهرېږي لکه :’’غرمه ، ژمے او داسې نور ‘‘</meaning></meanings></int></entry><entry><word>اسم صفت</word><int><pron/><gram>(اص)</gram><poem/><meanings><meaning>هغه اسم دے چې ترې نه د څۀ څيز حالت ياکېفيت څرګندېږي لکه ’’ خوږ ، کوږ او داسې نور ‘‘</meaning></meanings></int></entry><entry><word>اسم صوت</word><int><pron/><gram>(اص)</gram><poem/><meanings><meaning>هغه اسم دے چې د څۀ قسم اواز ، معنې په کښې برېښي لکه کړنګ ، ټک ټک ، اخ توخ ، شړنګ او داسې نور</meaning></meanings></int></entry><entry><word>اسم ضمير</word><int><pron/><gram>(اص)</gram><poem/><meanings><meaning>هغه ټکي چې د اسم په ځاے استعمالېږي لکه:’’زۀ ، تۀ ، هغه او داسې نور ‘‘</meaning></meanings></int></entry><entry><word>اسم ظرف</word><int><pron/><gram>(اص)</gram><poem/><meanings><meaning>هغه اسم دے چې د ځاے معنې په کښې څرګندېږي لکه : لوښے ، کور، جُمات او داسې نور</meaning></meanings></int></entry><entry><word>اسم عدد</word><int><pron/><gram>(اص)</gram><poem/><meanings><meaning>هغه اسم چې شمېره ترې ظاهرېږي لکه :’’ لس ، شل ، دېرش او داسې نور</meaning></meanings></int></entry><entry><word>اسم فاعل</word><int><pron/><gram>(اص)</gram><poem/><meanings><meaning>هغه اسم دے چې د کار کوونکي پته ترې لګي لکه ليکونکے ، څښونکے ، خوړونکے او داسې نور</meaning></meanings></int></entry><entry><word>اسم معرفه</word><int><pron/><gram>(اص)</gram><poem/><meanings><meaning>هغه اسم چې د خاص څيز يا فرد نوم ترې ظاهرېږي لکه : ’’احمد ، کوهاټ او داسې نور</meaning></meanings></int></entry><entry><word>اسم مفعول</word><int><pron/><gram>(اص)</gram><poem/><meanings><meaning>اسم دے چې هغه څيز يا فرد ترې ظاهرېږي په چا چې کار شوے وي لکه : ’’ وژلے شوے ، ټکېدلے شوے او داسې نور ‘‘</meaning></meanings></int></entry><entry><word>اسم مکبر</word><int><pron/><gram>(اص)</gram><poem/><meanings><meaning>هغه اسم چې د اصلي حالت په ځاے لوے والے ترې ظاهرېږي يا مبالغه وي په کښې لکه ’’ عالم نه علامه ، مرغۍ نه مارغۀ او داسې نور ‘‘</meaning></meanings></int></entry><entry><word>اسم نکره</word><int><pron/><gram>(اص)</gram><poem/><meanings><meaning>هغه اسم دے چې د خپل جنس د هر يو څيز دپاره استعمالېدے شي لکه ’’ ټوپۍ ، کوټ ، تُوره او داسې نور‘‘</meaning></meanings></int></entry><entry><word>اسمار</word><int><pron>( اَ+ س+ما+ ر )</pron><gram>[ اف : پ ، اس ، معر ، مذ ، وا]</gram><poem/><meanings><meaning>د کونړ سره نزدې د افغانستان د يوې علاقې نوم دے</meaning></meanings></int></entry><entry><word>اسمارے</word><int><pron>( اَ+س+مَا +رَے )</pron><gram>[ اف ، پ ، اس ، فا ع، مذ ، وا، ج : اسماري، (مؤ ، وا: اسمارۍ ) ]</gram><poem/><meanings><meaning>د اسمار سړے ، د اسمار اوسېدونکے</meaning><meaning>د ښځو نومونه هم وي</meaning></meanings></int></entry><entry><word>اسماعيل</word><int><pron>( اِ+ سْ+ما+عِ+يْ+ل )</pron><gram>[ع ، اس ، معر، مذ، وا]</gram><poem/><meanings><meaning>د يو پېغمبر نوم چې د حضرت ابراهيم عليه السلام زوے ؤ دۀ ته اسماعيل ذبيح الله هم وائي</meaning><meaning>د مسلمانانو يو نوم</meaning></meanings></int></entry><entry><word>اسماعيل شهيد</word><int><pron>( اِسماعيل  شَ+هِ+يْ+دْ )</pron><gram>[ اس ، معر، مذ، وا]</gram><poem/><meanings><meaning>دا مشهور او غازي د حضرت شاه ولي الله نمسے ؤ د سيد احمد شهيد بريلوي سره د سکانو خلاف په جنګ کښې شهيد شو مزار ئې په بالاکوټ کښې دے</meaning></meanings></int></entry><entry><word>اسماعيله</word><int><pron>( اِ+ سْ +ما+عِ+يْ+له )</pron><gram>[ پ ، اس ، معر ، مؤ ]</gram><poem/><meanings><meaning>اسمېله سمېله ، د مردان ضلعې د صوابۍ په تحصيل کښې يو کلے</meaning></meanings></int></entry><entry><word>اسماعيليه</word><int><pron>( اِ+ سْ+ما+عِ+ يْ+لِيْ+يَه )</pron><gram>[ ع ، اس ، معر ، مؤ ]</gram><poem/><meanings><meaning>د مسلمانانو يوه فرقه ددې فرقې مشر ته اغا خان وائي</meaning><meaning>نهر سوېز سره نزدې د يو ښار نوم</meaning></meanings></int></entry><entry><word>اسماعيلي</word><int><pron>( اِ+ سْ+ما+ عِ+يْ+لِ+يْ )</pron><gram>[ ع، اص ، ص ، مذ ، وا ، ج: اسماعيليان ]</gram><poem/><meanings><meaning>د اسماعيلي فرقې يو غړے</meaning></meanings></int></entry><entry><word>اسمان</word><int><pron>( اَ+س+ما+ن)</pron><gram>[ فا ، اس ، مذ ، وا ، ج : اسمانونه ]</gram><poem></poem><meanings><meaning>(و آسمان)</meaning></meanings></int></entry></words>
