<?xml version="1.0" encoding="UTF-8"?>
<words>
  <entry>
    <word>اتر</word>
    <int>
      <pron>(اَ+تَرْ)</pron>
      <gram>[ پ ، ف ، مهم ]</gram>
      <poem/>
      <meanings>
        <meaning>دا ټکے ځان ته هېڅ معنٰى نۀ لري  د خبر سره روستو وئيلے شي  لکه : ’’ د فلاني څۀ خبر اتر شته که نۀ ؟ ‘‘</meaning>
      </meanings>
    </int>
  </entry>
<entry><word>اترک بترک</word><int><pron>(اَتْ+رِکْ+بَتْ+رَکْ)</pron><gram>[ اف : پ ( قاموس) اس ص،مذ، وا، ج ( مؤ ، وا : اَترکه بترکه ، ج : اَترکې بترکې ) ]</gram><poem/><meanings><meaning>غريب ، بې وسيلې ، ميرات ، اوترک</meaning></meanings></int></entry><entry><word>اترنګ</word><int><pron>(اتَ+رَنْ+ګ)</pron><gram>[ اف : پ (قاموس ) اس ، مذ ، وا، ج : اترنګي ]</gram><poem>که د مئين په وينو رنګ دي&lt;br/&gt;زړونه اوکاږي په منګل ها (نور صاحب)</poem><meanings><meaning>د نکريزې ګل</meaning><meaning>يو بوټے دے چې د رنګولو په کار راځي او په دارو کښې هم استعمالېږي</meaning><meaning>په سوات کښې يو بوټے دے چې اَته قسمه ګلونه نيسي</meaning></meanings></int></entry><entry><word>اترول</word><int><pron>(اَتْ+رَ+وْ+لْ)</pron><gram>[ اف : پ ( قاموس ) مص ]</gram><poem/><meanings><meaning>خبرول ، د خبرول سره استعمالېږي  لکه : ’’ خبرول اترول  ‘‘</meaning></meanings></int></entry><entry><word>اتره</word><int><pron>( اَ + تْ + رَ )</pron><gram>[ پ ، ف مهم ]</gram><poem/><meanings><meaning>يواځې نۀ استعمالېږي ـ د خبرې سره وئيلې شي لکه : ’’ څۀ خبره اتره شته ؟ ‘‘</meaning></meanings></int><int><pron>(اَتْ+رَ)</pron><gram>[ پ ، اس ، مؤ ، وا ]</gram><poem>پور پوخ شي په کړي کښې جوش په پورته ووهينه&lt;br/&gt;ګوړي ئې په څمڅۍ باندې زر اوولي په اتره کښې	(ظفر)</poem><meanings><meaning/><meaning>لوے خاورين ښانک چې ګوړه په کښې جوړېږي</meaning><meaning>اف : د وجود پورتنۍ حصه ، د ملا نه تر غاړې پورې تنه</meaning></meanings></int></entry><entry><word>اترېدل</word><int><pron>(اَتْ+رې+دْ+لْ)</pron><gram>[ اف ، پ (قاموس) تا مهم]</gram><poem></poem><meanings><meaning>د خبرېدل مصدر سره استعمالېږي لکه:’’خبرېدل اترېدل‘‘</meaning><meaning></meaning></meanings></int></entry></words>
