<?xml version="1.0" encoding="UTF-8"?>
<words>
  <entry>
    <word>اوز</word>
    <int>
      <pron>( او+ز )</pron>
      <gram>[ اف ، پ ( قاموس ) مذ ]</gram>
      <poem/>
      <meanings>
        <meaning>عدد مجهول، دومره قدرې</meaning>
      </meanings>
    </int>
  </entry>
<entry><word>اوزار</word><int><pron>( اَو+زا+ر )</pron><gram>[ فا، اس ، مذ ، وا، ج ]</gram><poem/><meanings><meaning>کالي، رَچ، د کار اسباب، لکه : ځان سره خپل اوزار واخله ‘‘</meaning></meanings></int></entry><entry><word>اوزر</word><int><pron>( اُو+زَ+رْ )</pron><gram>[ پ ، اس ، مذ ، وا، ج : اُوزرونه ]</gram><poem/><meanings><meaning>وزر، عذر، د مړي فاتحه يا لاس نيوے</meaning></meanings></int></entry><entry><word>اوزر کول</word><int><pron/><gram/><poem/><meanings><meaning>(اص) د مړي فاتحه کول، د مړي لاس نيوے کول</meaning></meanings></int></entry><entry><word>اوزر مبارک</word><int><pron/><gram>(سو، اص)</gram><poem/><meanings><meaning>غم ښادي کول، مُبارکي او لاس نيوے کول</meaning></meanings></int></entry><entry><word>اوزغنجن</word><int><pron>( او+ز+غَ+نْ+ج+ن )</pron><gram>[ اف : پ (قاموس) ص ، مذ، (مؤ ، وا: اوزغنجنه ،و ج : اوزغنجنې ) ]</gram><poem/><meanings><meaning>اوژغنجن، د وژغنې نه جوړ څيز، د بزو د وېښتو نه جوړ څيز</meaning></meanings></int></entry><entry><word>اوزغنه</word><int><pron>( اُو+ز+غُ+نه )</pron><gram>[ اف : پ (قاموس) اس ،مؤ]</gram><poem/><meanings><meaning>د بزې وېښتۀ اوژغونه، وژغونه</meaning></meanings></int></entry><entry><word>اوز کے</word><int><pron>( اُو+ز+کَے )</pron><gram>[ پ (وز) اس ، مذ، وا، ج : اُوزکي ]</gram><poem/><meanings><meaning>د لرګو پېټے، د لرګو بار، وزاکائے</meaning></meanings></int></entry><entry><word>اوزګار</word><int><pron>( او+ز+ګا+ر)</pron><gram>[ پ ، ص ، مذ ، وا، ج ( مؤ ، وا: اوزګاره ، ج : اوزګارې ) ]</gram><poem/><meanings><meaning>وزګار، فارغه، ليه، بې کاره</meaning></meanings></int></entry><entry><word>اوزګار شوے</word><int><pron/><gram>(اف)</gram><poem/><meanings><meaning/><meaning>وزګار شوے، فارغ شوے، خالي شوے</meaning><meaning>بې کاره، د څۀکار نه ويستلے شوے</meaning></meanings></int></entry><entry><word>اوزګار کړے</word><int><pron/><gram>(اف)</gram><poem/><meanings><meaning>(و اوزګار شوے)</meaning></meanings></int></entry><entry><word>اوزګارتوب</word><int><pron>( اوزګار+تو+ب )</pron><gram>[ پ ، حمص ]</gram><poem/><meanings><meaning>وزګارتيا، وزګارېدنه، اوزګارتېب</meaning></meanings></int></entry><entry><word>اوزګارتيا</word><int><pron>( اوزګار+تِ+يا )</pron><gram>[ پ ، حمص ]</gram><poem/><meanings><meaning>(و اوزګارتوب)</meaning></meanings></int></entry><entry><word>اوزګار والے</word><int><pron/><gram>(اف)</gram><poem/><meanings><meaning>(و اوزګارتوب)</meaning></meanings></int></entry><entry><word>اوزګارول</word><int><pron>( او+ز+ګا+ رَ+وَ+ل )</pron><gram>[ پ ، مص ، مت ]</gram><poem/><meanings><meaning>ما : اوزګار کۀ، حا : اوزګاروي، ا : اوزګار به کي، امر: اوزګار که (د حال نه سېوا نور فعلونه د اوزګار کول نه وتي دي)</meaning><meaning>فارغول، وزګارول، خالي کول، بې کاره کول، د کار نه ويستل</meaning></meanings></int></entry><entry><word>اوزګارونګ</word><int><pron>( او+ز+ګا+ر+ وَ+نْ+ګ )</pron><gram>[ اف : پ (قاموس ) حمص]</gram><poem/><meanings><meaning>اوزګارونه، خالي کونه، فارغونه، بې کاره کونه، د څۀ کار نه ويستنه</meaning></meanings></int></entry><entry><word>اوزګارونه</word><int><pron>( او+ز+ګا+ر+و+نَه )</pron><gram>[ اف : پ (قاموس) حمص]</gram><poem/><meanings><meaning>(و اوزګارنګ)</meaning></meanings></int></entry><entry><word>اوزګار وونکے</word><int><pron>( او+ز+ګا+ر+وُو+ن+کے )</pron><gram>[ پ ، اس ، فا ع ، مذ ، وا، ج : اوزګاروُونکي ]</gram><poem/><meanings><meaning>وزګاروُونکے، فارغوونکے، خالي کوُونکے، بې کاره کوونکے، د کار ويستونکے</meaning></meanings></int></entry><entry><word>اوزګارېدل</word><int><pron>( او+ز+ګا+رې+د+ل )</pron><gram>[ پ ، مص لا ]</gram><poem/><meanings><meaning>ما: اوزګار شۀ، حا : اوزګارېږي، ا : اوزګار به شي (د حال نه سېوا نور فعلونه د اوزګار کېدل نه راوتي دي)</meaning><meaning>وزګارېدل، فارغېدل، خالي کېدل، فرصت موندل، بې کارَ کېدل</meaning></meanings></int></entry><entry><word>اوزګارېدنګ</word><int><pron>( او+ز+ګا+رې+د+نْ+ګ )</pron><gram>[ اف: پ (قاموس) حمص]</gram><poem/><meanings><meaning>اوزګارېدنه، وزګارېدنه، فارغېدنه، خالي کېدنه، بې کاره کېدنه، فرصت موندنه</meaning></meanings></int></entry><entry><word>اوزګارېدنه</word><int><pron>( او+ز+ګا+رې+د+نَه )</pron><gram>[ اف : پ (قاموس) حمص]</gram><poem/><meanings><meaning>(و اوزګارېدنګ)</meaning></meanings></int></entry><entry><word>اوزګارېدونکے</word><int><pron>( او+ز+ګا+رې +دُو+نْ+کَے )</pron><gram>[ پ ، اس ، فا ع ، مذ، وا،   ج : اوزګارېدونکي ]</gram><poem/><meanings><meaning>وزګارېدونکے، فارغېدونکے، خالي کېدونکے، بې کاره کېدونکے، فرصت موندونکے</meaning></meanings></int></entry><entry><word>اوزګارېدۀ</word><int><pron>( او+ز+ګا+رې+دَ، ۀ )</pron><gram>[ پ ، ص ]</gram><poem/><meanings><meaning>وزګارېدۀ، فارغېدۀ، خالي کېدۀ، فرصت موندلے کېدۀ، لکه : ’’ زما اوزګارېدۀ ګران دي ‘‘</meaning><meaning>بې کاره کېدۀ، د کار نه ويستلے کېدۀ</meaning></meanings></int></entry><entry><word>اوزګړے</word><int><pron>( اُو+ز+ګ+ړَے )</pron><gram>[ اف : پ (قاموس) اس ، مذ ، وا، ج : اُوزګړي ]</gram><poem/><meanings><meaning>د بزې نر، د چېلۍ نر، پسۀ، وَز</meaning></meanings></int></entry><entry><word>اوزمېيل</word><int><pron>( او+ ز+مې+يَل )</pron><gram>[ پ ، وز ، ب ، خ ، مص ]</gram><poem/><meanings><meaning>(و ازمايل)</meaning></meanings></int></entry><entry><word>اوزه</word><int><pron>( اُوْ+زَه )</pron><gram>[ پ (ګن) اس ، مؤ ، وا، ج : اُوزې ]</gram><poem/><meanings><meaning>بزه، چېلۍ، وُزه</meaning></meanings></int></entry><entry><word>اوزے</word><int><pron>( او+زَے )</pron><gram>[ اف : پ (قاموس) اس ، مذ ]</gram><poem/><meanings><meaning>وزر، لېچه، د پسۀ يوه پښه</meaning></meanings></int></entry><entry><word>اوزے اوزے کول</word><int><pron/><gram>(اف، اص)</gram><poem/><meanings><meaning>اندام اندام کول، په اندامونو بېلول</meaning></meanings></int></entry><entry><word>اوزےلکے</word><int><pron>( اُو+ز ے+ل+کَے )</pron><gram>[ اف : پ (قاموس ) اس ، مذ]</gram><poem/><meanings><meaning>يو قسم پۍ لرونکي واښۀ دي چې اوږدې اوږدې پاڼې ئې وي</meaning></meanings></int></entry><entry><word>اوزئيے</word><int><pron>( اُو+ز+ يَے )</pron><gram>[ اف : پ (قاموس) ص ، مذ ]</gram><poem></poem><meanings><meaning>د بزې سره تعلق لرونکے، د بزې، د وزې، وزئين</meaning></meanings></int></entry></words>
