<?xml version="1.0" encoding="UTF-8"?>
<words>
  <entry>
    <word>اکړ</word>
    <int>
      <pron>( اَ+ کَ+ړ )</pron>
      <gram>[ اف : پ ، (قاموس) اس ، ص ، مذ ، وا ( مؤ ، وا: اکړه ، ج : اکړې ) ]</gram>
      <poem/>
      <meanings>
        <meaning>شنډ ، اوچ ، ناامېده ، مايوسه</meaning>
      </meanings>
    </int>
  </entry>
<entry><word>اکړل</word><int><pron>( اُ+کْ+ړَ+لْ )</pron><gram>[ پ ، ف ما ]</gram><poem></poem><meanings><meaning>وکړل ، اوئے کړل</meaning></meanings></int></entry></words>
