<?xml version="1.0" encoding="UTF-8"?>
<words>
  <entry>
    <word>اشا</word>
    <int>
      <pron>( اَ+شا)</pron>
      <gram>[ اف : پ (قاموس ) اس ص ، مؤ ، وا، ج : اشاوي ]</gram>
      <poem/>
      <meanings>
        <meaning>بلا يروونکے څيز ، بؤ ، نامعلومه بلا</meaning>
      </meanings>
    </int>
  </entry>
<entry><word>اشا وهل</word><int><pron/><gram>(اص)</gram><poem/><meanings><meaning>بؤ وهل ، بلا وهل ، کنايةً خرابېدلو ته وائي</meaning></meanings></int></entry><entry><word>اشار</word><int><pron>( اَ+شا+رْ )</pron><gram>[ اف : پ (سيند) ص ، مذ ]</gram><poem/><meanings><meaning>تريخ ، چې خوږ نۀ وي لکه : ’’دا شے اشار دے ‘‘</meaning></meanings></int></entry><entry><word>اشارت</word><int><pron>( اِ+شا+رَ +تْ )</pron><gram>[ ع : اس ، مذ، وا ، ج : اشارتونه ]</gram><poem>هر چې لار په اشارت ښئ و کورته&lt;br/&gt;حېراني ده د هغو زلمو زور ته         (علي خان)&lt;br/&gt;په روانه اوبو راشه عمر ګوره&lt;br/&gt;ډېر دے هومره اشارت په دا دنيا        (رحمٰن بابا)&lt;br/&gt;وړکوټے ور دې مخامخ دے&lt;br/&gt;د غاړکۍ تعويذ دې کړي اشارتونه (ټپه)</poem><meanings><meaning>اشاره ، اِشوره د بل طرف ته ګوته نيول ،د سترګې په وهلو سره بل پوهه کول</meaning><meaning>نصيحت ، سبق ، لار ښودنه ،</meaning><meaning>په نمانځۀ کښې ګوته اوچتونه</meaning><meaning>مفعولي کنځل وائي چې هغه خو ايله اشارت غواړي ۔</meaning></meanings></int></entry><entry><word>اشارت کول</word><int><pron/><gram>(اص)</gram><poem/><meanings><meaning>ګوته نيول ، لاس نيول ، سترګه وهل ، اشاره کول د چا چاته ور مخه کول</meaning></meanings></int></entry><entry><word>اشارت کېدل</word><int><pron/><gram>(اص)</gram><poem/><meanings><meaning>اشاره کېدل ، د چا ورمخه کېدل ۔</meaning></meanings></int></entry><entry><word>اشارتوب</word><int><pron>( ا +شا+رْ+تو+بْ )</pron><gram>[ اف : پ (سيند) حمص ]</gram><poem/><meanings><meaning>تريخوالے اشارتيا</meaning></meanings></int></entry><entry><word>اشارتيا</word><int><pron>( اَ+ شا+رْ+تِ+يا )</pron><gram>[ اف : پ (سيند) ص، وا ، ج: اشارتياوے ]</gram><poem/><meanings><meaning>تريخوالے</meaning><meaning>کلکوالے ، سختي لکه : ’’ فلانے راسره اشارتيا کوي ‘‘</meaning></meanings></int></entry><entry><word>اشاره</word><int><pron>( اِ+شات+ره )</pron><gram>[ ع ، اس ، مؤ ، وا ،  ج: اشارې ]</gram><poem/><meanings><meaning>(و اشارت)</meaning></meanings></int></entry><entry><word>اشاره ورکول</word><int><pron/><gram>(اص)</gram><poem/><meanings><meaning>سترګه وهل</meaning><meaning>چاته د اشارې په ذريعه خبر ورکول ، لارښودل ،</meaning><meaning>څوک په څۀ خبره پوهه کول ، هېره خبره وريادول</meaning><meaning/></meanings></int></entry><entry><word>اشاره والے</word><int><pron>( اَ+ شا+ر+وا+لے )</pron><gram>[ اف : پ (سيند) ص]</gram><poem/><meanings><meaning>(و اشارتيا)</meaning></meanings></int></entry><entry><word>اشاړي</word><int><pron>( اَ+شا+ړ+يْ )</pron><gram>[ اف : پ (قاموس ) اس ، مذ ]</gram><poem/><meanings><meaning>د يوې غرئيزې ونې مېوه</meaning><meaning>ترخې خرمانۍ ، تروې مندتې ، ځنګلي مندتې</meaning><meaning>په باجوړ کښې د يو کلي نوم</meaning></meanings></int></entry><entry><word>اشاعت</word><int><pron>( اِ+شا+عَ+تْ )</pron><gram>[ ع ، اس ، مذ ، وا ، ج : اشاعتونه ]</gram><poem/><meanings><meaning>لْغ: خورول ، اص</meaning><meaning>چاپ کول ، شائع کول</meaning><meaning>د څۀ څيز د مشهورۍ دپاره پروپېګنډه کول</meaning></meanings></int></entry><entry><word>اشايل</word><int><pron>( اُ +شا+ يَلْ )</pron><gram>[ پ ( وز ) مص مت ]</gram><poem></poem><meanings><meaning>ښائل ،ښودل، شايل ، شال</meaning></meanings></int></entry></words>
