<?xml version="1.0" encoding="UTF-8"?>
<words>
  <entry>
    <word>بد غاږڤ</word>
    <int>
      <pron/>
      <gram/>
      <poem/>
      <meanings>
        <meaning>بد آوازه- خراب آوازواله- غړانګو.</meaning>
      </meanings>
    </int>
  </entry>
<entry><word>بد اصل</word><int><pron/><gram>(اص)</gram><poem/><meanings><meaning>بدذات ، کم اصل ، چې وينه ئې سوچه نۀ وي بد خويه کمينه</meaning></meanings></int></entry><entry><word>بد اعتقاد</word><int><pron/><gram>(اص)</gram><poem/><meanings><meaning>بې اعتقاده ، چې اعتقاد نۀ لري چې څۀ عقيده نۀ لري</meaning><meaning>خراب اعتقاد لرونکے ، لکه : ’’ هغه بداعتقاد ټوله خبره ورانه کړه ‘‘</meaning><meaning/></meanings></int></entry><entry><word>بد دعا</word><int><pron>( بد+دُ +عا )</pron><gram>[ فا ، اس ، ص ، مؤ ]</gram><poem/><meanings><meaning>ښېرې، ازار، د چا تباهي غوښتل، خداے تعالٰى ته د يوسړي د کمي سوال کول</meaning></meanings></int></entry><entry><word>بد دماغ</word><int><pron>( بد+دِ+ما+غ )</pron><gram>[ فا ، اس ، ص ، مذ ، وا، ( مؤ ، وا: بددماغه ، ج : بد دماغې ) ]</gram><poem/><meanings><meaning>(و بد دماغه)</meaning></meanings></int></entry><entry><word>بد دماغه</word><int><pron>( بد+دِ+ما+غَه )</pron><gram>[ پ ،اس،ص ، مؤ ، مذ ، وا، مؤ، ج: بد دماغې ]</gram><poem/><meanings><meaning>چې دماغ ئې خراب وي چې مازغۀ ئې ښۀ کار نۀ کوي</meaning><meaning>کبرجن، مغرور، بدخويه، تېز طبيعته</meaning></meanings></int></entry><entry><word>بد دماغي</word><int><pron>( بد+ دِ+ما+غِيْ )</pron><gram>[فا ، ص ، مؤ ، وا]</gram><poem/><meanings><meaning>کبر، غرور</meaning></meanings></int></entry><entry><word>بد ديانت</word><int><pron>( بد+دِ+يا+نَ+تْ )</pron><gram>[ فا ، اس ، ص ، مذ ،وا( مؤ ، وا: بد ديانته ، ج : بد ديانتې ]</gram><poem/><meanings><meaning>ټګ، امانت خوړونکے، خيانت کوونکے، بې اتباره، بې ايمانه</meaning></meanings></int></entry><entry><word>بد ديانته</word><int><pron>( بد+دِ+يا+نَ+ته )</pron><gram>[ پ ، اس ، ص، مؤ ، مذ ، وا، مؤ، ج : بد ديانتې ]</gram><poem/><meanings><meaning>(و بد ديانت)</meaning></meanings></int></entry><entry><word>بد ديانتي</word><int><pron>( بد+دِ+يا+نَ+تِيْ )</pron><gram>[ فا، ص ، مؤ ، وا ]</gram><poem/><meanings><meaning>ټګي، بې اتباري، خيانت کونه</meaning></meanings></int></entry><entry><word>بد ډوله</word><int><pron>( بد+ډَو+له )</pron><gram>[ پ ، ص ]</gram><poem/><meanings><meaning>بدشکله، بې ډوله، بد رنګ</meaning></meanings></int></entry><entry><word>بد ذات</word><int><pron>( بد+ذا+تْ )</pron><gram>[ فا ، اس ، ص، مذ( مؤ ، وا: بد ذاته ، ج : بـد ذاتې ) ]</gram><poem/><meanings><meaning>(و بد اصل)</meaning></meanings></int></entry><entry><word>بد ذاته</word><int><pron>( بد+ذا+تَه )</pron><gram>[ پ ،ا س، ص ، مؤ ، مذ ، وا، مؤ ، ج : بدذاتې]</gram><poem/><meanings><meaning>(و بد اصل)</meaning></meanings></int></entry><entry><word>بد ذاتي</word><int><pron>( بد+ذا+تِيْ )</pron><gram>[ فا، ص ، مؤ ، وا]</gram><poem/><meanings><meaning>کم اصلي، کمينه توب شېطاني، وران کاري</meaning></meanings></int></entry><entry><word>بد ذائقه</word><int><pron>( بد + ذا + ئې + قَه )</pron><gram>[ فا ، ص ، مذ]</gram><poem></poem><meanings><meaning>بې خونده ، چې خوند ئې خراب وي ـ</meaning></meanings></int></entry></words>
