<?xml version="1.0" encoding="UTF-8"?>
<words>
  <entry>
    <word>احرار</word>
    <int>
      <pron>( اَح+را+رْ )</pron>
      <gram>[ ع ، اس ، مذ ، ج ، وا : حُر ]</gram>
      <poem/>
      <meanings>
        <meaning>لُغ : ازاد ، بې وجې ، بې قېده ، اصيل  اص : د يو سياسي جماعت نوم</meaning>
      </meanings>
    </int>
  </entry>
<entry><word>احرام</word><int><pron>( اِ+ حْ+را+م )</pron><gram>[ ع ، اس ، مذ ، وا ، ج : احرامونه ]</gram><poem/><meanings><meaning>لُغ : په ځان حرامول، اص : د حج په ورځو کښې يو څو جائز کارونه په ځان بندول ، د مقررو ځايونو نه نيت تړل</meaning></meanings></int></entry><entry><word>احرام تړل</word><int><pron></pron><gram>(اص)</gram><poem></poem><meanings><meaning>د حج په موقع د يو خاص ځاے نه دوه څادره د ځان پټولو دپاره د ځان راتاوول او ځينې جائز کارونه په ځا ن حرامول</meaning></meanings></int></entry></words>
